[
  {
    "country_id": "AFG",
    "nom_officiel": "Afghanistan",
    "nom_court": "Afghanistan",
    "english_name": "Afghanistan",
    "iso2": "AF",
    "iso3": "AFG",
    "onu_status": "member_state",
    "continent": "Asie"
  },
  {
    "country_id": "ZAF",
    "nom_officiel": "Afrique du Sud",
    "nom_court": "Afrique du Sud",
    "english_name": "South Africa",
    "iso2": "ZA",
    "iso3": "ZAF",
    "onu_status": "member_state",
    "continent": "Afrique"
  },
  {
    "country_id": "ALB",
    "nom_officiel": "Albanie",
    "nom_court": "Albanie",
    "english_name": "Albania",
    "iso2": "AL",
    "iso3": "ALB",
    "onu_status": "member_state",
    "continent": "Europe"
  },
  {
    "country_id": "DZA",
    "nom_officiel": "Algérie",
    "nom_court": "Algérie",
    "english_name": "Algeria",
    "iso2": "DZ",
    "iso3": "DZA",
    "onu_status": "member_state",
    "continent": "Afrique"
  },
  {
    "country_id": "DEU",
    "nom_officiel": "Allemagne",
    "nom_court": "Allemagne",
    "english_name": "Germany",
    "iso2": "DE",
    "iso3": "DEU",
    "onu_status": "member_state",
    "continent": "Europe"
  },
  {
    "country_id": "AND",
    "nom_officiel": "Andorre",
    "nom_court": "Andorre",
    "english_name": "Andorra",
    "iso2": "AD",
    "iso3": "AND",
    "onu_status": "member_state",
    "continent": "Europe"
  },
  {
    "country_id": "AGO",
    "nom_officiel": "Angola",
    "nom_court": "Angola",
    "english_name": "Angola",
    "iso2": "AO",
    "iso3": "AGO",
    "onu_status": "member_state",
    "continent": "Afrique"
  },
  {
    "country_id": "ATG",
    "nom_officiel": "Antigua-et-Barbuda",
    "nom_court": "Antigua-et-Barbuda",
    "english_name": "Antigua and Barbuda",
    "iso2": "AG",
    "iso3": "ATG",
    "onu_status": "member_state",
    "continent": "Amérique du Nord"
  },
  {
    "country_id": "SAU",
    "nom_officiel": "Arabie Saoudite",
    "nom_court": "Arabie Saoudite",
    "english_name": "Saudi Arabia",
    "iso2": "SA",
    "iso3": "SAU",
    "onu_status": "member_state",
    "continent": "Asie"
  },
  {
    "country_id": "ARG",
    "nom_officiel": "Argentine",
    "nom_court": "Argentine",
    "english_name": "Argentina",
    "iso2": "AR",
    "iso3": "ARG",
    "onu_status": "member_state",
    "continent": "Amérique du Sud"
  },
  {
    "country_id": "ARM",
    "nom_officiel": "Arménie",
    "nom_court": "Arménie",
    "english_name": "Armenia",
    "iso2": "AM",
    "iso3": "ARM",
    "onu_status": "member_state",
    "continent": "Asie"
  },
  {
    "country_id": "AUS",
    "nom_officiel": "Australie",
    "nom_court": "Australie",
    "english_name": "Australia",
    "iso2": "AU",
    "iso3": "AUS",
    "onu_status": "member_state",
    "continent": "Océanie"
  },
  {
    "country_id": "AUT",
    "nom_officiel": "Autriche",
    "nom_court": "Autriche",
    "english_name": "Austria",
    "iso2": "AT",
    "iso3": "AUT",
    "onu_status": "member_state",
    "continent": "Europe"
  },
  {
    "country_id": "AZE",
    "nom_officiel": "Azerbaïdjan",
    "nom_court": "Azerbaïdjan",
    "english_name": "Azerbaijan",
    "iso2": "AZ",
    "iso3": "AZE",
    "onu_status": "member_state",
    "continent": "Asie"
  },
  {
    "country_id": "BHS",
    "nom_officiel": "Bahamas",
    "nom_court": "Bahamas",
    "english_name": "Bahamas",
    "iso2": "BS",
    "iso3": "BHS",
    "onu_status": "member_state",
    "continent": "Amérique du Nord"
  },
  {
    "country_id": "BHR",
    "nom_officiel": "Bahreïn",
    "nom_court": "Bahreïn",
    "english_name": "Bahrain",
    "iso2": "BH",
    "iso3": "BHR",
    "onu_status": "member_state",
    "continent": "Asie"
  },
  {
    "country_id": "BGD",
    "nom_officiel": "Bangladesh",
    "nom_court": "Bangladesh",
    "english_name": "Bangladesh",
    "iso2": "BD",
    "iso3": "BGD",
    "onu_status": "member_state",
    "continent": "Asie"
  },
  {
    "country_id": "BRB",
    "nom_officiel": "Barbade",
    "nom_court": "Barbade",
    "english_name": "Barbados",
    "iso2": "BB",
    "iso3": "BRB",
    "onu_status": "member_state",
    "continent": "Amérique du Nord"
  },
  {
    "country_id": "BEL",
    "nom_officiel": "Belgique",
    "nom_court": "Belgique",
    "english_name": "Belgium",
    "iso2": "BE",
    "iso3": "BEL",
    "onu_status": "member_state",
    "continent": "Europe"
  },
  {
    "country_id": "BLZ",
    "nom_officiel": "Belize",
    "nom_court": "Belize",
    "english_name": "Belize",
    "iso2": "BZ",
    "iso3": "BLZ",
    "onu_status": "member_state",
    "continent": "Amérique du Nord"
  },
  {
    "country_id": "BTN",
    "nom_officiel": "Bhoutan",
    "nom_court": "Bhoutan",
    "english_name": "Bhutan",
    "iso2": "BT",
    "iso3": "BTN",
    "onu_status": "member_state",
    "continent": "Asie"
  },
  {
    "country_id": "MMR",
    "nom_officiel": "Birmanie",
    "nom_court": "Birmanie",
    "english_name": "Myanmar",
    "iso2": "MM",
    "iso3": "MMR",
    "onu_status": "member_state",
    "continent": "Asie"
  },
  {
    "country_id": "BLR",
    "nom_officiel": "Biélorussie",
    "nom_court": "Biélorussie",
    "english_name": "Belarus",
    "iso2": "BY",
    "iso3": "BLR",
    "onu_status": "member_state",
    "continent": "Europe"
  },
  {
    "country_id": "BOL",
    "nom_officiel": "Bolivie",
    "nom_court": "Bolivie",
    "english_name": "Bolivia",
    "iso2": "BO",
    "iso3": "BOL",
    "onu_status": "member_state",
    "continent": "Amérique du Sud"
  },
  {
    "country_id": "BIH",
    "nom_officiel": "Bosnie-Herzégovine",
    "nom_court": "Bosnie-Herzégovine",
    "english_name": "Bosnia and Herzegovina",
    "iso2": "BA",
    "iso3": "BIH",
    "onu_status": "member_state",
    "continent": "Europe"
  },
  {
    "country_id": "BWA",
    "nom_officiel": "Botswana",
    "nom_court": "Botswana",
    "english_name": "Botswana",
    "iso2": "BW",
    "iso3": "BWA",
    "onu_status": "member_state",
    "continent": "Afrique"
  },
  {
    "country_id": "BRN",
    "nom_officiel": "Brunei",
    "nom_court": "Brunei",
    "english_name": "Brunei",
    "iso2": "BN",
    "iso3": "BRN",
    "onu_status": "member_state",
    "continent": "Asie"
  },
  {
    "country_id": "BRA",
    "nom_officiel": "Brésil",
    "nom_court": "Brésil",
    "english_name": "Brazil",
    "iso2": "BR",
    "iso3": "BRA",
    "onu_status": "member_state",
    "continent": "Amérique du Sud"
  },
  {
    "country_id": "BGR",
    "nom_officiel": "Bulgarie",
    "nom_court": "Bulgarie",
    "english_name": "Bulgaria",
    "iso2": "BG",
    "iso3": "BGR",
    "onu_status": "member_state",
    "continent": "Europe"
  },
  {
    "country_id": "BFA",
    "nom_officiel": "Burkina Faso",
    "nom_court": "Burkina Faso",
    "english_name": "Burkina Faso",
    "iso2": "BF",
    "iso3": "BFA",
    "onu_status": "member_state",
    "continent": "Afrique"
  },
  {
    "country_id": "BDI",
    "nom_officiel": "Burundi",
    "nom_court": "Burundi",
    "english_name": "Burundi",
    "iso2": "BI",
    "iso3": "BDI",
    "onu_status": "member_state",
    "continent": "Afrique"
  },
  {
    "country_id": "BEN",
    "nom_officiel": "Bénin",
    "nom_court": "Bénin",
    "english_name": "Benin",
    "iso2": "BJ",
    "iso3": "BEN",
    "onu_status": "member_state",
    "continent": "Afrique"
  },
  {
    "country_id": "KHM",
    "nom_officiel": "Cambodge",
    "nom_court": "Cambodge",
    "english_name": "Cambodia",
    "iso2": "KH",
    "iso3": "KHM",
    "onu_status": "member_state",
    "continent": "Asie"
  },
  {
    "country_id": "CMR",
    "nom_officiel": "Cameroun",
    "nom_court": "Cameroun",
    "english_name": "Cameroon",
    "iso2": "CM",
    "iso3": "CMR",
    "onu_status": "member_state",
    "continent": "Afrique"
  },
  {
    "country_id": "CAN",
    "nom_officiel": "Canada",
    "nom_court": "Canada",
    "english_name": "Canada",
    "iso2": "CA",
    "iso3": "CAN",
    "onu_status": "member_state",
    "continent": "Amérique du Nord"
  },
  {
    "country_id": "CHL",
    "nom_officiel": "Chili",
    "nom_court": "Chili",
    "english_name": "Chile",
    "iso2": "CL",
    "iso3": "CHL",
    "onu_status": "member_state",
    "continent": "Amérique du Sud"
  },
  {
    "country_id": "CHN",
    "nom_officiel": "Chine",
    "nom_court": "Chine",
    "english_name": "China",
    "iso2": "CN",
    "iso3": "CHN",
    "onu_status": "member_state",
    "continent": "Asie"
  },
  {
    "country_id": "CYP",
    "nom_officiel": "Chypre",
    "nom_court": "Chypre",
    "english_name": "Cyprus",
    "iso2": "CY",
    "iso3": "CYP",
    "onu_status": "member_state",
    "continent": "Europe"
  },
  {
    "country_id": "VAT",
    "nom_officiel": "Cité du Vatican",
    "nom_court": "Cité du Vatican",
    "english_name": "Vatican City",
    "iso2": "VA",
    "iso3": "VAT",
    "onu_status": "observer_state",
    "continent": "Europe"
  },
  {
    "country_id": "COL",
    "nom_officiel": "Colombie",
    "nom_court": "Colombie",
    "english_name": "Colombia",
    "iso2": "CO",
    "iso3": "COL",
    "onu_status": "member_state",
    "continent": "Amérique du Sud"
  },
  {
    "country_id": "COM",
    "nom_officiel": "Comores",
    "nom_court": "Comores",
    "english_name": "Comoros",
    "iso2": "KM",
    "iso3": "COM",
    "onu_status": "member_state",
    "continent": "Afrique"
  },
  {
    "country_id": "COG",
    "nom_officiel": "Congo",
    "nom_court": "Congo",
    "english_name": "Republic of the Congo",
    "iso2": "CG",
    "iso3": "COG",
    "onu_status": "member_state",
    "continent": "Afrique"
  },
  {
    "country_id": "COD",
    "nom_officiel": "Congo (Rép. dém.)",
    "nom_court": "Congo (Rép. dém.)",
    "english_name": "DR Congo",
    "iso2": "CD",
    "iso3": "COD",
    "onu_status": "member_state",
    "continent": "Afrique"
  },
  {
    "country_id": "PRK",
    "nom_officiel": "Corée du Nord",
    "nom_court": "Corée du Nord",
    "english_name": "North Korea",
    "iso2": "KP",
    "iso3": "PRK",
    "onu_status": "member_state",
    "continent": "Asie"
  },
  {
    "country_id": "KOR",
    "nom_officiel": "Corée du Sud",
    "nom_court": "Corée du Sud",
    "english_name": "South Korea",
    "iso2": "KR",
    "iso3": "KOR",
    "onu_status": "member_state",
    "continent": "Asie"
  },
  {
    "country_id": "CRI",
    "nom_officiel": "Costa Rica",
    "nom_court": "Costa Rica",
    "english_name": "Costa Rica",
    "iso2": "CR",
    "iso3": "CRI",
    "onu_status": "member_state",
    "continent": "Amérique du Nord"
  },
  {
    "country_id": "HRV",
    "nom_officiel": "Croatie",
    "nom_court": "Croatie",
    "english_name": "Croatia",
    "iso2": "HR",
    "iso3": "HRV",
    "onu_status": "member_state",
    "continent": "Europe"
  },
  {
    "country_id": "CUB",
    "nom_officiel": "Cuba",
    "nom_court": "Cuba",
    "english_name": "Cuba",
    "iso2": "CU",
    "iso3": "CUB",
    "onu_status": "member_state",
    "continent": "Amérique du Nord"
  },
  {
    "country_id": "CIV",
    "nom_officiel": "Côte d'Ivoire",
    "nom_court": "Côte d'Ivoire",
    "english_name": "Ivory Coast",
    "iso2": "CI",
    "iso3": "CIV",
    "onu_status": "member_state",
    "continent": "Afrique"
  },
  {
    "country_id": "DNK",
    "nom_officiel": "Danemark",
    "nom_court": "Danemark",
    "english_name": "Denmark",
    "iso2": "DK",
    "iso3": "DNK",
    "onu_status": "member_state",
    "continent": "Europe"
  },
  {
    "country_id": "DJI",
    "nom_officiel": "Djibouti",
    "nom_court": "Djibouti",
    "english_name": "Djibouti",
    "iso2": "DJ",
    "iso3": "DJI",
    "onu_status": "member_state",
    "continent": "Afrique"
  },
  {
    "country_id": "DMA",
    "nom_officiel": "Dominique",
    "nom_court": "Dominique",
    "english_name": "Dominica",
    "iso2": "DM",
    "iso3": "DMA",
    "onu_status": "member_state",
    "continent": "Amérique du Nord"
  },
  {
    "country_id": "ESP",
    "nom_officiel": "Espagne",
    "nom_court": "Espagne",
    "english_name": "Spain",
    "iso2": "ES",
    "iso3": "ESP",
    "onu_status": "member_state",
    "continent": "Europe"
  },
  {
    "country_id": "EST",
    "nom_officiel": "Estonie",
    "nom_court": "Estonie",
    "english_name": "Estonia",
    "iso2": "EE",
    "iso3": "EST",
    "onu_status": "member_state",
    "continent": "Europe"
  },
  {
    "country_id": "FJI",
    "nom_officiel": "Fidji",
    "nom_court": "Fidji",
    "english_name": "Fiji",
    "iso2": "FJ",
    "iso3": "FJI",
    "onu_status": "member_state",
    "continent": "Océanie"
  },
  {
    "country_id": "FIN",
    "nom_officiel": "Finlande",
    "nom_court": "Finlande",
    "english_name": "Finland",
    "iso2": "FI",
    "iso3": "FIN",
    "onu_status": "member_state",
    "continent": "Europe"
  },
  {
    "country_id": "FRA",
    "nom_officiel": "France",
    "nom_court": "France",
    "english_name": "France",
    "iso2": "FR",
    "iso3": "FRA",
    "onu_status": "member_state",
    "continent": "Europe"
  },
  {
    "country_id": "GAB",
    "nom_officiel": "Gabon",
    "nom_court": "Gabon",
    "english_name": "Gabon",
    "iso2": "GA",
    "iso3": "GAB",
    "onu_status": "member_state",
    "continent": "Afrique"
  },
  {
    "country_id": "GMB",
    "nom_officiel": "Gambie",
    "nom_court": "Gambie",
    "english_name": "Gambia",
    "iso2": "GM",
    "iso3": "GMB",
    "onu_status": "member_state",
    "continent": "Afrique"
  },
  {
    "country_id": "GHA",
    "nom_officiel": "Ghana",
    "nom_court": "Ghana",
    "english_name": "Ghana",
    "iso2": "GH",
    "iso3": "GHA",
    "onu_status": "member_state",
    "continent": "Afrique"
  },
  {
    "country_id": "GRD",
    "nom_officiel": "Grenade",
    "nom_court": "Grenade",
    "english_name": "Grenada",
    "iso2": "GD",
    "iso3": "GRD",
    "onu_status": "member_state",
    "continent": "Amérique du Nord"
  },
  {
    "country_id": "GRC",
    "nom_officiel": "Grèce",
    "nom_court": "Grèce",
    "english_name": "Greece",
    "iso2": "GR",
    "iso3": "GRC",
    "onu_status": "member_state",
    "continent": "Europe"
  },
  {
    "country_id": "GTM",
    "nom_officiel": "Guatemala",
    "nom_court": "Guatemala",
    "english_name": "Guatemala",
    "iso2": "GT",
    "iso3": "GTM",
    "onu_status": "member_state",
    "continent": "Amérique du Nord"
  },
  {
    "country_id": "GIN",
    "nom_officiel": "Guinée",
    "nom_court": "Guinée",
    "english_name": "Guinea",
    "iso2": "GN",
    "iso3": "GIN",
    "onu_status": "member_state",
    "continent": "Afrique"
  },
  {
    "country_id": "GNQ",
    "nom_officiel": "Guinée équatoriale",
    "nom_court": "Guinée équatoriale",
    "english_name": "Equatorial Guinea",
    "iso2": "GQ",
    "iso3": "GNQ",
    "onu_status": "member_state",
    "continent": "Afrique"
  },
  {
    "country_id": "GNB",
    "nom_officiel": "Guinée-Bissau",
    "nom_court": "Guinée-Bissau",
    "english_name": "Guinea-Bissau",
    "iso2": "GW",
    "iso3": "GNB",
    "onu_status": "member_state",
    "continent": "Afrique"
  },
  {
    "country_id": "GUY",
    "nom_officiel": "Guyana",
    "nom_court": "Guyana",
    "english_name": "Guyana",
    "iso2": "GY",
    "iso3": "GUY",
    "onu_status": "member_state",
    "continent": "Amérique du Sud"
  },
  {
    "country_id": "GEO",
    "nom_officiel": "Géorgie",
    "nom_court": "Géorgie",
    "english_name": "Georgia",
    "iso2": "GE",
    "iso3": "GEO",
    "onu_status": "member_state",
    "continent": "Asie"
  },
  {
    "country_id": "HTI",
    "nom_officiel": "Haïti",
    "nom_court": "Haïti",
    "english_name": "Haiti",
    "iso2": "HT",
    "iso3": "HTI",
    "onu_status": "member_state",
    "continent": "Amérique du Nord"
  },
  {
    "country_id": "HND",
    "nom_officiel": "Honduras",
    "nom_court": "Honduras",
    "english_name": "Honduras",
    "iso2": "HN",
    "iso3": "HND",
    "onu_status": "member_state",
    "continent": "Amérique du Nord"
  },
  {
    "country_id": "HUN",
    "nom_officiel": "Hongrie",
    "nom_court": "Hongrie",
    "english_name": "Hungary",
    "iso2": "HU",
    "iso3": "HUN",
    "onu_status": "member_state",
    "continent": "Europe"
  },
  {
    "country_id": "IND",
    "nom_officiel": "Inde",
    "nom_court": "Inde",
    "english_name": "India",
    "iso2": "IN",
    "iso3": "IND",
    "onu_status": "member_state",
    "continent": "Asie"
  },
  {
    "country_id": "IDN",
    "nom_officiel": "Indonésie",
    "nom_court": "Indonésie",
    "english_name": "Indonesia",
    "iso2": "ID",
    "iso3": "IDN",
    "onu_status": "member_state",
    "continent": "Asie"
  },
  {
    "country_id": "IRQ",
    "nom_officiel": "Irak",
    "nom_court": "Irak",
    "english_name": "Iraq",
    "iso2": "IQ",
    "iso3": "IRQ",
    "onu_status": "member_state",
    "continent": "Asie"
  },
  {
    "country_id": "IRN",
    "nom_officiel": "Iran",
    "nom_court": "Iran",
    "english_name": "Iran",
    "iso2": "IR",
    "iso3": "IRN",
    "onu_status": "member_state",
    "continent": "Asie"
  },
  {
    "country_id": "IRL",
    "nom_officiel": "Irlande",
    "nom_court": "Irlande",
    "english_name": "Ireland",
    "iso2": "IE",
    "iso3": "IRL",
    "onu_status": "member_state",
    "continent": "Europe"
  },
  {
    "country_id": "ISL",
    "nom_officiel": "Islande",
    "nom_court": "Islande",
    "english_name": "Iceland",
    "iso2": "IS",
    "iso3": "ISL",
    "onu_status": "member_state",
    "continent": "Europe"
  },
  {
    "country_id": "ISR",
    "nom_officiel": "Israël",
    "nom_court": "Israël",
    "english_name": "Israel",
    "iso2": "IL",
    "iso3": "ISR",
    "onu_status": "member_state",
    "continent": "Asie"
  },
  {
    "country_id": "ITA",
    "nom_officiel": "Italie",
    "nom_court": "Italie",
    "english_name": "Italy",
    "iso2": "IT",
    "iso3": "ITA",
    "onu_status": "member_state",
    "continent": "Europe"
  },
  {
    "country_id": "JAM",
    "nom_officiel": "Jamaïque",
    "nom_court": "Jamaïque",
    "english_name": "Jamaica",
    "iso2": "JM",
    "iso3": "JAM",
    "onu_status": "member_state",
    "continent": "Amérique du Nord"
  },
  {
    "country_id": "JPN",
    "nom_officiel": "Japon",
    "nom_court": "Japon",
    "english_name": "Japan",
    "iso2": "JP",
    "iso3": "JPN",
    "onu_status": "member_state",
    "continent": "Asie"
  },
  {
    "country_id": "JOR",
    "nom_officiel": "Jordanie",
    "nom_court": "Jordanie",
    "english_name": "Jordan",
    "iso2": "JO",
    "iso3": "JOR",
    "onu_status": "member_state",
    "continent": "Asie"
  },
  {
    "country_id": "KAZ",
    "nom_officiel": "Kazakhstan",
    "nom_court": "Kazakhstan",
    "english_name": "Kazakhstan",
    "iso2": "KZ",
    "iso3": "KAZ",
    "onu_status": "member_state",
    "continent": "Asie"
  },
  {
    "country_id": "KEN",
    "nom_officiel": "Kenya",
    "nom_court": "Kenya",
    "english_name": "Kenya",
    "iso2": "KE",
    "iso3": "KEN",
    "onu_status": "member_state",
    "continent": "Afrique"
  },
  {
    "country_id": "KGZ",
    "nom_officiel": "Kirghizistan",
    "nom_court": "Kirghizistan",
    "english_name": "Kyrgyzstan",
    "iso2": "KG",
    "iso3": "KGZ",
    "onu_status": "member_state",
    "continent": "Asie"
  },
  {
    "country_id": "KIR",
    "nom_officiel": "Kiribati",
    "nom_court": "Kiribati",
    "english_name": "Kiribati",
    "iso2": "KI",
    "iso3": "KIR",
    "onu_status": "member_state",
    "continent": "Océanie"
  },
  {
    "country_id": "KWT",
    "nom_officiel": "Koweït",
    "nom_court": "Koweït",
    "english_name": "Kuwait",
    "iso2": "KW",
    "iso3": "KWT",
    "onu_status": "member_state",
    "continent": "Asie"
  },
  {
    "country_id": "LAO",
    "nom_officiel": "Laos",
    "nom_court": "Laos",
    "english_name": "Laos",
    "iso2": "LA",
    "iso3": "LAO",
    "onu_status": "member_state",
    "continent": "Asie"
  },
  {
    "country_id": "LSO",
    "nom_officiel": "Lesotho",
    "nom_court": "Lesotho",
    "english_name": "Lesotho",
    "iso2": "LS",
    "iso3": "LSO",
    "onu_status": "member_state",
    "continent": "Afrique"
  },
  {
    "country_id": "LVA",
    "nom_officiel": "Lettonie",
    "nom_court": "Lettonie",
    "english_name": "Latvia",
    "iso2": "LV",
    "iso3": "LVA",
    "onu_status": "member_state",
    "continent": "Europe"
  },
  {
    "country_id": "LBN",
    "nom_officiel": "Liban",
    "nom_court": "Liban",
    "english_name": "Lebanon",
    "iso2": "LB",
    "iso3": "LBN",
    "onu_status": "member_state",
    "continent": "Asie"
  },
  {
    "country_id": "LBR",
    "nom_officiel": "Liberia",
    "nom_court": "Liberia",
    "english_name": "Liberia",
    "iso2": "LR",
    "iso3": "LBR",
    "onu_status": "member_state",
    "continent": "Afrique"
  },
  {
    "country_id": "LBY",
    "nom_officiel": "Libye",
    "nom_court": "Libye",
    "english_name": "Libya",
    "iso2": "LY",
    "iso3": "LBY",
    "onu_status": "member_state",
    "continent": "Afrique"
  },
  {
    "country_id": "LIE",
    "nom_officiel": "Liechtenstein",
    "nom_court": "Liechtenstein",
    "english_name": "Liechtenstein",
    "iso2": "LI",
    "iso3": "LIE",
    "onu_status": "member_state",
    "continent": "Europe"
  },
  {
    "country_id": "LTU",
    "nom_officiel": "Lituanie",
    "nom_court": "Lituanie",
    "english_name": "Lithuania",
    "iso2": "LT",
    "iso3": "LTU",
    "onu_status": "member_state",
    "continent": "Europe"
  },
  {
    "country_id": "LUX",
    "nom_officiel": "Luxembourg",
    "nom_court": "Luxembourg",
    "english_name": "Luxembourg",
    "iso2": "LU",
    "iso3": "LUX",
    "onu_status": "member_state",
    "continent": "Europe"
  },
  {
    "country_id": "MKD",
    "nom_officiel": "Macédoine du Nord",
    "nom_court": "Macédoine du Nord",
    "english_name": "North Macedonia",
    "iso2": "MK",
    "iso3": "MKD",
    "onu_status": "member_state",
    "continent": "Europe"
  },
  {
    "country_id": "MDG",
    "nom_officiel": "Madagascar",
    "nom_court": "Madagascar",
    "english_name": "Madagascar",
    "iso2": "MG",
    "iso3": "MDG",
    "onu_status": "member_state",
    "continent": "Afrique"
  },
  {
    "country_id": "MYS",
    "nom_officiel": "Malaisie",
    "nom_court": "Malaisie",
    "english_name": "Malaysia",
    "iso2": "MY",
    "iso3": "MYS",
    "onu_status": "member_state",
    "continent": "Asie"
  },
  {
    "country_id": "MWI",
    "nom_officiel": "Malawi",
    "nom_court": "Malawi",
    "english_name": "Malawi",
    "iso2": "MW",
    "iso3": "MWI",
    "onu_status": "member_state",
    "continent": "Afrique"
  },
  {
    "country_id": "MDV",
    "nom_officiel": "Maldives",
    "nom_court": "Maldives",
    "english_name": "Maldives",
    "iso2": "MV",
    "iso3": "MDV",
    "onu_status": "member_state",
    "continent": "Asie"
  },
  {
    "country_id": "MLI",
    "nom_officiel": "Mali",
    "nom_court": "Mali",
    "english_name": "Mali",
    "iso2": "ML",
    "iso3": "MLI",
    "onu_status": "member_state",
    "continent": "Afrique"
  },
  {
    "country_id": "MLT",
    "nom_officiel": "Malte",
    "nom_court": "Malte",
    "english_name": "Malta",
    "iso2": "MT",
    "iso3": "MLT",
    "onu_status": "member_state",
    "continent": "Europe"
  },
  {
    "country_id": "MAR",
    "nom_officiel": "Maroc",
    "nom_court": "Maroc",
    "english_name": "Morocco",
    "iso2": "MA",
    "iso3": "MAR",
    "onu_status": "member_state",
    "continent": "Afrique"
  },
  {
    "country_id": "MRT",
    "nom_officiel": "Mauritanie",
    "nom_court": "Mauritanie",
    "english_name": "Mauritania",
    "iso2": "MR",
    "iso3": "MRT",
    "onu_status": "member_state",
    "continent": "Afrique"
  },
  {
    "country_id": "MEX",
    "nom_officiel": "Mexique",
    "nom_court": "Mexique",
    "english_name": "Mexico",
    "iso2": "MX",
    "iso3": "MEX",
    "onu_status": "member_state",
    "continent": "Amérique du Nord"
  },
  {
    "country_id": "FSM",
    "nom_officiel": "Micronésie",
    "nom_court": "Micronésie",
    "english_name": "Micronesia",
    "iso2": "FM",
    "iso3": "FSM",
    "onu_status": "member_state",
    "continent": "Océanie"
  },
  {
    "country_id": "MDA",
    "nom_officiel": "Moldavie",
    "nom_court": "Moldavie",
    "english_name": "Moldova",
    "iso2": "MD",
    "iso3": "MDA",
    "onu_status": "member_state",
    "continent": "Europe"
  },
  {
    "country_id": "MCO",
    "nom_officiel": "Monaco",
    "nom_court": "Monaco",
    "english_name": "Monaco",
    "iso2": "MC",
    "iso3": "MCO",
    "onu_status": "member_state",
    "continent": "Europe"
  },
  {
    "country_id": "MNG",
    "nom_officiel": "Mongolie",
    "nom_court": "Mongolie",
    "english_name": "Mongolia",
    "iso2": "MN",
    "iso3": "MNG",
    "onu_status": "member_state",
    "continent": "Asie"
  },
  {
    "country_id": "MNE",
    "nom_officiel": "Monténégro",
    "nom_court": "Monténégro",
    "english_name": "Montenegro",
    "iso2": "ME",
    "iso3": "MNE",
    "onu_status": "member_state",
    "continent": "Europe"
  },
  {
    "country_id": "MOZ",
    "nom_officiel": "Mozambique",
    "nom_court": "Mozambique",
    "english_name": "Mozambique",
    "iso2": "MZ",
    "iso3": "MOZ",
    "onu_status": "member_state",
    "continent": "Afrique"
  },
  {
    "country_id": "NAM",
    "nom_officiel": "Namibie",
    "nom_court": "Namibie",
    "english_name": "Namibia",
    "iso2": "NA",
    "iso3": "NAM",
    "onu_status": "member_state",
    "continent": "Afrique"
  },
  {
    "country_id": "NRU",
    "nom_officiel": "Nauru",
    "nom_court": "Nauru",
    "english_name": "Nauru",
    "iso2": "NR",
    "iso3": "NRU",
    "onu_status": "member_state",
    "continent": "Océanie"
  },
  {
    "country_id": "NIC",
    "nom_officiel": "Nicaragua",
    "nom_court": "Nicaragua",
    "english_name": "Nicaragua",
    "iso2": "NI",
    "iso3": "NIC",
    "onu_status": "member_state",
    "continent": "Amérique du Nord"
  },
  {
    "country_id": "NER",
    "nom_officiel": "Niger",
    "nom_court": "Niger",
    "english_name": "Niger",
    "iso2": "NE",
    "iso3": "NER",
    "onu_status": "member_state",
    "continent": "Afrique"
  },
  {
    "country_id": "NGA",
    "nom_officiel": "Nigéria",
    "nom_court": "Nigéria",
    "english_name": "Nigeria",
    "iso2": "NG",
    "iso3": "NGA",
    "onu_status": "member_state",
    "continent": "Afrique"
  },
  {
    "country_id": "NOR",
    "nom_officiel": "Norvège",
    "nom_court": "Norvège",
    "english_name": "Norway",
    "iso2": "NO",
    "iso3": "NOR",
    "onu_status": "member_state",
    "continent": "Europe"
  },
  {
    "country_id": "NZL",
    "nom_officiel": "Nouvelle-Zélande",
    "nom_court": "Nouvelle-Zélande",
    "english_name": "New Zealand",
    "iso2": "NZ",
    "iso3": "NZL",
    "onu_status": "member_state",
    "continent": "Océanie"
  },
  {
    "country_id": "NPL",
    "nom_officiel": "Népal",
    "nom_court": "Népal",
    "english_name": "Nepal",
    "iso2": "NP",
    "iso3": "NPL",
    "onu_status": "member_state",
    "continent": "Asie"
  },
  {
    "country_id": "OMN",
    "nom_officiel": "Oman",
    "nom_court": "Oman",
    "english_name": "Oman",
    "iso2": "OM",
    "iso3": "OMN",
    "onu_status": "member_state",
    "continent": "Asie"
  },
  {
    "country_id": "UGA",
    "nom_officiel": "Ouganda",
    "nom_court": "Ouganda",
    "english_name": "Uganda",
    "iso2": "UG",
    "iso3": "UGA",
    "onu_status": "member_state",
    "continent": "Afrique"
  },
  {
    "country_id": "UZB",
    "nom_officiel": "Ouzbékistan",
    "nom_court": "Ouzbékistan",
    "english_name": "Uzbekistan",
    "iso2": "UZ",
    "iso3": "UZB",
    "onu_status": "member_state",
    "continent": "Asie"
  },
  {
    "country_id": "PAK",
    "nom_officiel": "Pakistan",
    "nom_court": "Pakistan",
    "english_name": "Pakistan",
    "iso2": "PK",
    "iso3": "PAK",
    "onu_status": "member_state",
    "continent": "Asie"
  },
  {
    "country_id": "PLW",
    "nom_officiel": "Palaos (Palau)",
    "nom_court": "Palaos (Palau)",
    "english_name": "Palau",
    "iso2": "PW",
    "iso3": "PLW",
    "onu_status": "member_state",
    "continent": "Océanie"
  },
  {
    "country_id": "PSE",
    "nom_officiel": "Palestine",
    "nom_court": "Palestine",
    "english_name": "Palestine",
    "iso2": "PS",
    "iso3": "PSE",
    "onu_status": "observer_state",
    "continent": "Asie"
  },
  {
    "country_id": "PAN",
    "nom_officiel": "Panama",
    "nom_court": "Panama",
    "english_name": "Panama",
    "iso2": "PA",
    "iso3": "PAN",
    "onu_status": "member_state",
    "continent": "Amérique du Nord"
  },
  {
    "country_id": "PNG",
    "nom_officiel": "Papouasie-Nouvelle-Guinée",
    "nom_court": "Papouasie-Nouvelle-Guinée",
    "english_name": "Papua New Guinea",
    "iso2": "PG",
    "iso3": "PNG",
    "onu_status": "member_state",
    "continent": "Océanie"
  },
  {
    "country_id": "PRY",
    "nom_officiel": "Paraguay",
    "nom_court": "Paraguay",
    "english_name": "Paraguay",
    "iso2": "PY",
    "iso3": "PRY",
    "onu_status": "member_state",
    "continent": "Amérique du Sud"
  },
  {
    "country_id": "NLD",
    "nom_officiel": "Pays-Bas",
    "nom_court": "Pays-Bas",
    "english_name": "Netherlands",
    "iso2": "NL",
    "iso3": "NLD",
    "onu_status": "member_state",
    "continent": "Europe"
  },
  {
    "country_id": "PHL",
    "nom_officiel": "Philippines",
    "nom_court": "Philippines",
    "english_name": "Philippines",
    "iso2": "PH",
    "iso3": "PHL",
    "onu_status": "member_state",
    "continent": "Asie"
  },
  {
    "country_id": "POL",
    "nom_officiel": "Pologne",
    "nom_court": "Pologne",
    "english_name": "Poland",
    "iso2": "PL",
    "iso3": "POL",
    "onu_status": "member_state",
    "continent": "Europe"
  },
  {
    "country_id": "PRT",
    "nom_officiel": "Portugal",
    "nom_court": "Portugal",
    "english_name": "Portugal",
    "iso2": "PT",
    "iso3": "PRT",
    "onu_status": "member_state",
    "continent": "Europe"
  },
  {
    "country_id": "PER",
    "nom_officiel": "Pérou",
    "nom_court": "Pérou",
    "english_name": "Peru",
    "iso2": "PE",
    "iso3": "PER",
    "onu_status": "member_state",
    "continent": "Amérique du Sud"
  },
  {
    "country_id": "QAT",
    "nom_officiel": "Qatar",
    "nom_court": "Qatar",
    "english_name": "Qatar",
    "iso2": "QA",
    "iso3": "QAT",
    "onu_status": "member_state",
    "continent": "Asie"
  },
  {
    "country_id": "ROU",
    "nom_officiel": "Roumanie",
    "nom_court": "Roumanie",
    "english_name": "Romania",
    "iso2": "RO",
    "iso3": "ROU",
    "onu_status": "member_state",
    "continent": "Europe"
  },
  {
    "country_id": "GBR",
    "nom_officiel": "Royaume-Uni",
    "nom_court": "Royaume-Uni",
    "english_name": "United Kingdom",
    "iso2": "GB",
    "iso3": "GBR",
    "onu_status": "member_state",
    "continent": "Europe"
  },
  {
    "country_id": "RUS",
    "nom_officiel": "Russie",
    "nom_court": "Russie",
    "english_name": "Russia",
    "iso2": "RU",
    "iso3": "RUS",
    "onu_status": "member_state",
    "continent": "Europe"
  },
  {
    "country_id": "RWA",
    "nom_officiel": "Rwanda",
    "nom_court": "Rwanda",
    "english_name": "Rwanda",
    "iso2": "RW",
    "iso3": "RWA",
    "onu_status": "member_state",
    "continent": "Afrique"
  },
  {
    "country_id": "CAF",
    "nom_officiel": "République centrafricaine",
    "nom_court": "République centrafricaine",
    "english_name": "Central African Republic",
    "iso2": "CF",
    "iso3": "CAF",
    "onu_status": "member_state",
    "continent": "Afrique"
  },
  {
    "country_id": "DOM",
    "nom_officiel": "République dominicaine",
    "nom_court": "République dominicaine",
    "english_name": "Dominican Republic",
    "iso2": "DO",
    "iso3": "DOM",
    "onu_status": "member_state",
    "continent": "Amérique du Nord"
  },
  {
    "country_id": "KNA",
    "nom_officiel": "Saint-Christophe-et-Niévès",
    "nom_court": "Saint-Christophe-et-Niévès",
    "english_name": "Saint Kitts and Nevis",
    "iso2": "KN",
    "iso3": "KNA",
    "onu_status": "member_state",
    "continent": "Amérique du Nord"
  },
  {
    "country_id": "SMR",
    "nom_officiel": "Saint-Marin",
    "nom_court": "Saint-Marin",
    "english_name": "San Marino",
    "iso2": "SM",
    "iso3": "SMR",
    "onu_status": "member_state",
    "continent": "Europe"
  },
  {
    "country_id": "VCT",
    "nom_officiel": "Saint-Vincent-et-les-Grenadines",
    "nom_court": "Saint-Vincent-et-les-Grenadines",
    "english_name": "Saint Vincent and the Grenadines",
    "iso2": "VC",
    "iso3": "VCT",
    "onu_status": "member_state",
    "continent": "Amérique du Nord"
  },
  {
    "country_id": "LCA",
    "nom_officiel": "Sainte-Lucie",
    "nom_court": "Sainte-Lucie",
    "english_name": "Saint Lucia",
    "iso2": "LC",
    "iso3": "LCA",
    "onu_status": "member_state",
    "continent": "Amérique du Nord"
  },
  {
    "country_id": "SLV",
    "nom_officiel": "Salvador",
    "nom_court": "Salvador",
    "english_name": "El Salvador",
    "iso2": "SV",
    "iso3": "SLV",
    "onu_status": "member_state",
    "continent": "Amérique du Nord"
  },
  {
    "country_id": "WSM",
    "nom_officiel": "Samoa",
    "nom_court": "Samoa",
    "english_name": "Samoa",
    "iso2": "WS",
    "iso3": "WSM",
    "onu_status": "member_state",
    "continent": "Océanie"
  },
  {
    "country_id": "SRB",
    "nom_officiel": "Serbie",
    "nom_court": "Serbie",
    "english_name": "Serbia",
    "iso2": "RS",
    "iso3": "SRB",
    "onu_status": "member_state",
    "continent": "Europe"
  },
  {
    "country_id": "SYC",
    "nom_officiel": "Seychelles",
    "nom_court": "Seychelles",
    "english_name": "Seychelles",
    "iso2": "SC",
    "iso3": "SYC",
    "onu_status": "member_state",
    "continent": "Afrique"
  },
  {
    "country_id": "SLE",
    "nom_officiel": "Sierra Leone",
    "nom_court": "Sierra Leone",
    "english_name": "Sierra Leone",
    "iso2": "SL",
    "iso3": "SLE",
    "onu_status": "member_state",
    "continent": "Afrique"
  },
  {
    "country_id": "SGP",
    "nom_officiel": "Singapour",
    "nom_court": "Singapour",
    "english_name": "Singapore",
    "iso2": "SG",
    "iso3": "SGP",
    "onu_status": "member_state",
    "continent": "Asie"
  },
  {
    "country_id": "SVK",
    "nom_officiel": "Slovaquie",
    "nom_court": "Slovaquie",
    "english_name": "Slovakia",
    "iso2": "SK",
    "iso3": "SVK",
    "onu_status": "member_state",
    "continent": "Europe"
  },
  {
    "country_id": "SVN",
    "nom_officiel": "Slovénie",
    "nom_court": "Slovénie",
    "english_name": "Slovenia",
    "iso2": "SI",
    "iso3": "SVN",
    "onu_status": "member_state",
    "continent": "Europe"
  },
  {
    "country_id": "SOM",
    "nom_officiel": "Somalie",
    "nom_court": "Somalie",
    "english_name": "Somalia",
    "iso2": "SO",
    "iso3": "SOM",
    "onu_status": "member_state",
    "continent": "Afrique"
  },
  {
    "country_id": "SDN",
    "nom_officiel": "Soudan",
    "nom_court": "Soudan",
    "english_name": "Sudan",
    "iso2": "SD",
    "iso3": "SDN",
    "onu_status": "member_state",
    "continent": "Afrique"
  },
  {
    "country_id": "SSD",
    "nom_officiel": "Soudan du Sud",
    "nom_court": "Soudan du Sud",
    "english_name": "South Sudan",
    "iso2": "SS",
    "iso3": "SSD",
    "onu_status": "member_state",
    "continent": "Afrique"
  },
  {
    "country_id": "LKA",
    "nom_officiel": "Sri Lanka",
    "nom_court": "Sri Lanka",
    "english_name": "Sri Lanka",
    "iso2": "LK",
    "iso3": "LKA",
    "onu_status": "member_state",
    "continent": "Asie"
  },
  {
    "country_id": "CHE",
    "nom_officiel": "Suisse",
    "nom_court": "Suisse",
    "english_name": "Switzerland",
    "iso2": "CH",
    "iso3": "CHE",
    "onu_status": "member_state",
    "continent": "Europe"
  },
  {
    "country_id": "SUR",
    "nom_officiel": "Surinam",
    "nom_court": "Surinam",
    "english_name": "Suriname",
    "iso2": "SR",
    "iso3": "SUR",
    "onu_status": "member_state",
    "continent": "Amérique du Sud"
  },
  {
    "country_id": "SWE",
    "nom_officiel": "Suède",
    "nom_court": "Suède",
    "english_name": "Sweden",
    "iso2": "SE",
    "iso3": "SWE",
    "onu_status": "member_state",
    "continent": "Europe"
  },
  {
    "country_id": "SWZ",
    "nom_officiel": "Swaziland",
    "nom_court": "Swaziland",
    "english_name": "Eswatini",
    "iso2": "SZ",
    "iso3": "SWZ",
    "onu_status": "member_state",
    "continent": "Afrique"
  },
  {
    "country_id": "SYR",
    "nom_officiel": "Syrie",
    "nom_court": "Syrie",
    "english_name": "Syria",
    "iso2": "SY",
    "iso3": "SYR",
    "onu_status": "member_state",
    "continent": "Asie"
  },
  {
    "country_id": "STP",
    "nom_officiel": "São Tomé et Príncipe",
    "nom_court": "São Tomé et Príncipe",
    "english_name": "São Tomé and Príncipe",
    "iso2": "ST",
    "iso3": "STP",
    "onu_status": "member_state",
    "continent": "Afrique"
  },
  {
    "country_id": "SEN",
    "nom_officiel": "Sénégal",
    "nom_court": "Sénégal",
    "english_name": "Senegal",
    "iso2": "SN",
    "iso3": "SEN",
    "onu_status": "member_state",
    "continent": "Afrique"
  },
  {
    "country_id": "TJK",
    "nom_officiel": "Tadjikistan",
    "nom_court": "Tadjikistan",
    "english_name": "Tajikistan",
    "iso2": "TJ",
    "iso3": "TJK",
    "onu_status": "member_state",
    "continent": "Asie"
  },
  {
    "country_id": "TZA",
    "nom_officiel": "Tanzanie",
    "nom_court": "Tanzanie",
    "english_name": "Tanzania",
    "iso2": "TZ",
    "iso3": "TZA",
    "onu_status": "member_state",
    "continent": "Afrique"
  },
  {
    "country_id": "TCD",
    "nom_officiel": "Tchad",
    "nom_court": "Tchad",
    "english_name": "Chad",
    "iso2": "TD",
    "iso3": "TCD",
    "onu_status": "member_state",
    "continent": "Afrique"
  },
  {
    "country_id": "CZE",
    "nom_officiel": "Tchéquie",
    "nom_court": "Tchéquie",
    "english_name": "Czechia",
    "iso2": "CZ",
    "iso3": "CZE",
    "onu_status": "member_state",
    "continent": "Europe"
  },
  {
    "country_id": "THA",
    "nom_officiel": "Thaïlande",
    "nom_court": "Thaïlande",
    "english_name": "Thailand",
    "iso2": "TH",
    "iso3": "THA",
    "onu_status": "member_state",
    "continent": "Asie"
  },
  {
    "country_id": "TLS",
    "nom_officiel": "Timor oriental",
    "nom_court": "Timor oriental",
    "english_name": "Timor-Leste",
    "iso2": "TL",
    "iso3": "TLS",
    "onu_status": "member_state",
    "continent": "Asie"
  },
  {
    "country_id": "TGO",
    "nom_officiel": "Togo",
    "nom_court": "Togo",
    "english_name": "Togo",
    "iso2": "TG",
    "iso3": "TGO",
    "onu_status": "member_state",
    "continent": "Afrique"
  },
  {
    "country_id": "TON",
    "nom_officiel": "Tonga",
    "nom_court": "Tonga",
    "english_name": "Tonga",
    "iso2": "TO",
    "iso3": "TON",
    "onu_status": "member_state",
    "continent": "Océanie"
  },
  {
    "country_id": "TTO",
    "nom_officiel": "Trinité-et-Tobago",
    "nom_court": "Trinité-et-Tobago",
    "english_name": "Trinidad and Tobago",
    "iso2": "TT",
    "iso3": "TTO",
    "onu_status": "member_state",
    "continent": "Amérique du Nord"
  },
  {
    "country_id": "TUN",
    "nom_officiel": "Tunisie",
    "nom_court": "Tunisie",
    "english_name": "Tunisia",
    "iso2": "TN",
    "iso3": "TUN",
    "onu_status": "member_state",
    "continent": "Afrique"
  },
  {
    "country_id": "TKM",
    "nom_officiel": "Turkménistan",
    "nom_court": "Turkménistan",
    "english_name": "Turkmenistan",
    "iso2": "TM",
    "iso3": "TKM",
    "onu_status": "member_state",
    "continent": "Asie"
  },
  {
    "country_id": "TUR",
    "nom_officiel": "Turquie",
    "nom_court": "Turquie",
    "english_name": "Türkiye",
    "iso2": "TR",
    "iso3": "TUR",
    "onu_status": "member_state",
    "continent": "Asie"
  },
  {
    "country_id": "TUV",
    "nom_officiel": "Tuvalu",
    "nom_court": "Tuvalu",
    "english_name": "Tuvalu",
    "iso2": "TV",
    "iso3": "TUV",
    "onu_status": "member_state",
    "continent": "Océanie"
  },
  {
    "country_id": "UKR",
    "nom_officiel": "Ukraine",
    "nom_court": "Ukraine",
    "english_name": "Ukraine",
    "iso2": "UA",
    "iso3": "UKR",
    "onu_status": "member_state",
    "continent": "Europe"
  },
  {
    "country_id": "URY",
    "nom_officiel": "Uruguay",
    "nom_court": "Uruguay",
    "english_name": "Uruguay",
    "iso2": "UY",
    "iso3": "URY",
    "onu_status": "member_state",
    "continent": "Amérique du Sud"
  },
  {
    "country_id": "VUT",
    "nom_officiel": "Vanuatu",
    "nom_court": "Vanuatu",
    "english_name": "Vanuatu",
    "iso2": "VU",
    "iso3": "VUT",
    "onu_status": "member_state",
    "continent": "Océanie"
  },
  {
    "country_id": "VEN",
    "nom_officiel": "Venezuela",
    "nom_court": "Venezuela",
    "english_name": "Venezuela",
    "iso2": "VE",
    "iso3": "VEN",
    "onu_status": "member_state",
    "continent": "Amérique du Sud"
  },
  {
    "country_id": "VNM",
    "nom_officiel": "Viêt Nam",
    "nom_court": "Viêt Nam",
    "english_name": "Vietnam",
    "iso2": "VN",
    "iso3": "VNM",
    "onu_status": "member_state",
    "continent": "Asie"
  },
  {
    "country_id": "YEM",
    "nom_officiel": "Yémen",
    "nom_court": "Yémen",
    "english_name": "Yemen",
    "iso2": "YE",
    "iso3": "YEM",
    "onu_status": "member_state",
    "continent": "Asie"
  },
  {
    "country_id": "ZMB",
    "nom_officiel": "Zambie",
    "nom_court": "Zambie",
    "english_name": "Zambia",
    "iso2": "ZM",
    "iso3": "ZMB",
    "onu_status": "member_state",
    "continent": "Afrique"
  },
  {
    "country_id": "ZWE",
    "nom_officiel": "Zimbabwe",
    "nom_court": "Zimbabwe",
    "english_name": "Zimbabwe",
    "iso2": "ZW",
    "iso3": "ZWE",
    "onu_status": "member_state",
    "continent": "Afrique"
  },
  {
    "country_id": "EGY",
    "nom_officiel": "Égypte",
    "nom_court": "Égypte",
    "english_name": "Egypt",
    "iso2": "EG",
    "iso3": "EGY",
    "onu_status": "member_state",
    "continent": "Afrique"
  },
  {
    "country_id": "ARE",
    "nom_officiel": "Émirats arabes unis",
    "nom_court": "Émirats arabes unis",
    "english_name": "United Arab Emirates",
    "iso2": "AE",
    "iso3": "ARE",
    "onu_status": "member_state",
    "continent": "Asie"
  },
  {
    "country_id": "ECU",
    "nom_officiel": "Équateur",
    "nom_court": "Équateur",
    "english_name": "Ecuador",
    "iso2": "EC",
    "iso3": "ECU",
    "onu_status": "member_state",
    "continent": "Amérique du Sud"
  },
  {
    "country_id": "ERI",
    "nom_officiel": "Érythrée",
    "nom_court": "Érythrée",
    "english_name": "Eritrea",
    "iso2": "ER",
    "iso3": "ERI",
    "onu_status": "member_state",
    "continent": "Afrique"
  },
  {
    "country_id": "USA",
    "nom_officiel": "États-Unis",
    "nom_court": "États-Unis",
    "english_name": "United States",
    "iso2": "US",
    "iso3": "USA",
    "onu_status": "member_state",
    "continent": "Amérique du Nord"
  },
  {
    "country_id": "ETH",
    "nom_officiel": "Éthiopie",
    "nom_court": "Éthiopie",
    "english_name": "Ethiopia",
    "iso2": "ET",
    "iso3": "ETH",
    "onu_status": "member_state",
    "continent": "Afrique"
  },
  {
    "country_id": "MUS",
    "nom_officiel": "Île Maurice",
    "nom_court": "Île Maurice",
    "english_name": "Mauritius",
    "iso2": "MU",
    "iso3": "MUS",
    "onu_status": "member_state",
    "continent": "Afrique"
  },
  {
    "country_id": "MHL",
    "nom_officiel": "Îles Marshall",
    "nom_court": "Îles Marshall",
    "english_name": "Marshall Islands",
    "iso2": "MH",
    "iso3": "MHL",
    "onu_status": "member_state",
    "continent": "Océanie"
  },
  {
    "country_id": "SLB",
    "nom_officiel": "Îles Salomon",
    "nom_court": "Îles Salomon",
    "english_name": "Solomon Islands",
    "iso2": "SB",
    "iso3": "SLB",
    "onu_status": "member_state",
    "continent": "Océanie"
  },
  {
    "country_id": "CPV",
    "nom_officiel": "Îles du Cap-Vert",
    "nom_court": "Îles du Cap-Vert",
    "english_name": "Cape Verde",
    "iso2": "CV",
    "iso3": "CPV",
    "onu_status": "member_state",
    "continent": "Afrique"
  }
]
